cmdcheatsheet/__init__.py
cmdcheatsheet/cmdcheatsheet.py
cmdcheatsheet/alt_store/__init__.py
cmdcheatsheet/alt_store/actions.py
cmdcheatsheet/alt_store/add_alt_store.py
cmdcheatsheet/alt_store/core.py
cmdcheatsheet/alt_store/delete_alt_store.py
cmdcheatsheet/alt_store/display.py
cmdcheatsheet/alt_store/display_applied_alt_store_name.py
cmdcheatsheet/alt_store/display_available_alt_stores.py
cmdcheatsheet/alt_store/messages.py
cmdcheatsheet/alt_store/models.py
cmdcheatsheet/alt_store/switch_to_alt_store.py
cmdcheatsheet/alt_store/update_alt_store.py
cmdcheatsheet/commands/__init__.py
cmdcheatsheet/commands/actions.py
cmdcheatsheet/commands/add_command.py
cmdcheatsheet/commands/available_command_names.py
cmdcheatsheet/commands/commands.py
cmdcheatsheet/commands/core.py
cmdcheatsheet/commands/delete_command.py
cmdcheatsheet/commands/detailed_commands.py
cmdcheatsheet/commands/detailed_find_command.py
cmdcheatsheet/commands/detailed_global_find_command.py
cmdcheatsheet/commands/display.py
cmdcheatsheet/commands/find_command.py
cmdcheatsheet/commands/global_find_command.py
cmdcheatsheet/commands/messages.py
cmdcheatsheet/commands/table_view_commands.py
cmdcheatsheet/commands/table_view_find_command.py
cmdcheatsheet/commands/update_command.py
cmdcheatsheet/config/__init__.py
cmdcheatsheet/config/actions.py
cmdcheatsheet/config/alt_store_display_strategy.py
cmdcheatsheet/config/consts.py
cmdcheatsheet/config/core.py
cmdcheatsheet/config/default_display_strategy.py
cmdcheatsheet/config/display.py
cmdcheatsheet/config/display_available_configs.py
cmdcheatsheet/config/display_config.py
cmdcheatsheet/config/models.py
cmdcheatsheet/config/remove_config.py
cmdcheatsheet/config/set_config.py
cmdcheatsheet/config/set_config_to_default.py
cmdcheatsheet/config/set_single_config_to_default.py
cmdcheatsheet/config/validators.py
cmdcheatsheet/general/__init__.py
cmdcheatsheet/general/actions.py
cmdcheatsheet/general/consts.py
cmdcheatsheet/general/core.py
cmdcheatsheet-0.0.48.dist-info/LICENSE
cmdcheatsheet-0.0.48.dist-info/METADATA
cmdcheatsheet-0.0.48.dist-info/WHEEL
cmdcheatsheet-0.0.48.dist-info/entry_points.txt
cmdcheatsheet-0.0.48.dist-info/top_level.txt
cmdcheatsheet-0.0.48.dist-info/RECORD
