Metadata-Version: 2.1
Name: cmdcheatsheet
Version: 0.0.48
Summary: Terminal commands cheat sheet helper
Home-page: https://github.com/obaranovskyi/cmdcheatsheet
Author: obaranovskyi (Oleh Baranovskyi)
Author-email: <oleh.baranovskyi.dev.acc@gmail.com>
License: MIT
Keywords: python,command,terminal,console,utilities
Classifier: Environment :: Console
Classifier: Intended Audience :: Developers
Classifier: Programming Language :: Python :: 3
Classifier: Operating System :: Unix
Classifier: Operating System :: MacOS
Classifier: Topic :: Utilities
License-File: LICENSE
Requires-Dist: rich
